auth_module/__init__.py
auth_module/config.py
auth_module/controllers.py
auth_module/middleware.py
auth_module/models.py
auth_module/services.py
auth_module/utils.py
auth_module-0.2.0.dist-info/LICENSE
auth_module-0.2.0.dist-info/METADATA
auth_module-0.2.0.dist-info/WHEEL
auth_module-0.2.0.dist-info/top_level.txt
auth_module-0.2.0.dist-info/RECORD
