Metadata-Version: 2.2
Name: auth_module
Version: 0.2.0
Summary: A reusable authentication module for Python applications
Home-page: https://github.com/drunksoul2021/auth_module
Author: Wesley
Author-email: drunksoul2023@gmail.com
Classifier: Programming Language :: Python :: 3
Classifier: License :: OSI Approved :: MIT License
Classifier: Operating System :: OS Independent
Requires-Python: >=3.8
License-File: LICENSE
Requires-Dist: pyjwt==2.8.0
Requires-Dist: python-dotenv==1.0.0
Requires-Dist: argon2-cffi==23.1.0
Dynamic: author
Dynamic: author-email
Dynamic: classifier
Dynamic: description
Dynamic: description-content-type
Dynamic: home-page
Dynamic: requires-dist
Dynamic: requires-python
Dynamic: summary
